MANIFEST.in
README.md
setup.py
config/__init__.py
config/default.py
mementoembed/__init__.py
mementoembed/archiveresource.py
mementoembed/favicon.py
mementoembed/imageselection.py
mementoembed/mementodocreel.py
mementoembed/mementoimagereel.py
mementoembed/mementoresource.py
mementoembed/mementosurrogate.py
mementoembed/mementothumbnail.py
mementoembed/mementowordcloud.py
mementoembed/originalresource.py
mementoembed/pagedata.py
mementoembed/seedresource.py
mementoembed/sessions.py
mementoembed/textprocessing.py
mementoembed/version.py
mementoembed.egg-info/PKG-INFO
mementoembed.egg-info/SOURCES.txt
mementoembed.egg-info/dependency_links.txt
mementoembed.egg-info/requires.txt
mementoembed.egg-info/top_level.txt
mementoembed.egg-info/zip-safe
mementoembed/services/__init__.py
mementoembed/services/errors.py
mementoembed/services/memento.py
mementoembed/services/oembed.py
mementoembed/services/product.py
mementoembed/static/css/bootstrap-grid.css
mementoembed/static/css/bootstrap-grid.css.map
mementoembed/static/css/bootstrap-grid.min.css
mementoembed/static/css/bootstrap-grid.min.css.map
mementoembed/static/css/bootstrap-reboot.css
mementoembed/static/css/bootstrap-reboot.css.map
mementoembed/static/css/bootstrap-reboot.min.css
mementoembed/static/css/bootstrap-reboot.min.css.map
mementoembed/static/css/bootstrap.css
mementoembed/static/css/bootstrap.css.map
mementoembed/static/css/bootstrap.min.css
mementoembed/static/css/bootstrap.min.css.map
mementoembed/static/css/sticky-footer-navbar.css
mementoembed/static/fonts/OpenSans-Regular.ttf
mementoembed/static/images/96px-Sphere_wireframe.svg.png
mementoembed/static/images/activity.gif
mementoembed/static/images/ajax-loader.gif
mementoembed/static/images/downarrow.png
mementoembed/static/images/microlink-example.png
mementoembed/static/js/bootstrap.bundle.js
mementoembed/static/js/bootstrap.bundle.js.map
mementoembed/static/js/bootstrap.bundle.min.js
mementoembed/static/js/bootstrap.bundle.min.js.map
mementoembed/static/js/bootstrap.js
mementoembed/static/js/bootstrap.js.map
mementoembed/static/js/bootstrap.min.js
mementoembed/static/js/bootstrap.min.js.map
mementoembed/static/js/create_screenshot.js
