Metadata-Version: 2.1
Name: mementoembed
Version: 0.2021.2.22.22825
Summary: UNKNOWN
Home-page: https://github.com/oduwsdl/MementoEmbed
Author: Shawn M. Jones
Author-email: jones.shawn.m@gmail.com
License: MIT
Keywords: webarchives memento embeds nlp
Platform: UNKNOWN
Classifier: Development Status :: 4 - Beta
Classifier: Intended Audience :: Developers
Classifier: Intended Audience :: Information Technology
Classifier: Intended Audience :: Science/Research
Classifier: Natural Language :: English
Classifier: Topic :: Internet :: WWW/HTTP
Classifier: Topic :: Text Processing
Classifier: Topic :: Scientific/Engineering
Classifier: Topic :: Scientific/Engineering :: Information Analysis
Classifier: Topic :: Scientific/Engineering :: Visualization
Classifier: Topic :: Software Development :: Libraries :: Python Modules
Classifier: Topic :: Utilities
Classifier: License :: OSI Approved :: MIT License
Classifier: Programming Language :: Python :: 3.7
